.gitignore
MANIFEST.in
Makefile
README.md
requirements.txt
setup.py
.github/workflows/pythonpackage.yml
notebooks/.keep
notebooks/Functions_Timestamp_and_Geolocation_EXIF.ipynb
notebooks/Functions_Timestamp_and_Geolocation_EXIF.ipynb:Zone.Identifier
notebooks/MTCNN.ipynb
notebooks/Meme_classification.ipynb
notebooks/Untitled.ipynb
notebooks/detecting_screenshots.ipynb
notebooks/duplicate_photos.ipynb
notebooks/face_clustering.ipynb
notebooks/face_recog_library.ipynb
notebooks/preprocessing_pipeline.ipynb
notebooks/similar_images.ipynb
notebooks/similarity.ipynb
photosorganisation/__init__.py
photosorganisation/blurry_classifier.py
photosorganisation/data.py
photosorganisation/duplicates.py
photosorganisation/geo_comment_tags.py
photosorganisation/get_total_size.py
photosorganisation/meme_classifier.py
photosorganisation/people_detecting.py
photosorganisation/photomulticlassifier.py
photosorganisation/photos.py
photosorganisation/screenshot_classifier.py
photosorganisation/similar_photos.py
photosorganisation.egg-info/PKG-INFO
photosorganisation.egg-info/SOURCES.txt
photosorganisation.egg-info/dependency_links.txt
photosorganisation.egg-info/not-zip-safe
photosorganisation.egg-info/requires.txt
photosorganisation.egg-info/top_level.txt
photosorganisation/data/.keep
photosorganisation/trained_models/blur_detector.h5
photosorganisation/trained_models/cnn_screenshots.h5
photosorganisation/trained_models/meme_classifier.h5
photosorganisation/trained_models/photo_multi_classifier.h5
scripts/photosorganisation-run
tests/__init__.py