Metadata-Version: 1.0
Name: photosorganisation
Version: 1.0.2.3
Summary: This python Package helps you sort and organize photos.Duplicates,Memes,Screenshots and Blurry Photos are identifed.Photos are tagged and classified for Geo-Location, Selfies,Animals etc.
Home-page: UNKNOWN
Author: UNKNOWN
Author-email: UNKNOWN
License: UNKNOWN
Platform: UNKNOWN
